finally_data_logger/__init__.py
finally_data_logger/client/__init__.py
finally_data_logger/client/data_logger.py
finally_data_logger/server/__init__.py
finally_data_logger/server/finally_data_logger_server.py
finally_data_logger-0.2.0.dist-info/METADATA
finally_data_logger-0.2.0.dist-info/WHEEL
finally_data_logger-0.2.0.dist-info/entry_points.txt
finally_data_logger-0.2.0.dist-info/top_level.txt
finally_data_logger-0.2.0.dist-info/RECORD
