Metadata-Version: 2.1
Name: finally-data-logger
Version: 0.2.0
Summary: A simple data logging server and client.
Home-page: https://github.com/arbasli2/FinallyDataLogger
Author: arbasli
Author-email: arbasli2@gmail.com
Classifier: Development Status :: 4 - Beta
Classifier: Intended Audience :: Developers
Classifier: License :: OSI Approved :: MIT License
Classifier: Programming Language :: Python :: 3
Classifier: Programming Language :: Python :: 3.6
Classifier: Programming Language :: Python :: 3.7
Classifier: Programming Language :: Python :: 3.8
Classifier: Programming Language :: Python :: 3.9
Requires-Dist: flask
Requires-Dist: requests
Requires-Dist: tinydb
Requires-Dist: numpy
